my_interactive_plots/__init__.py
my_interactive_plots/cli.py
my_interactive_plots/config.py
my_interactive_plots/data_loader.py
my_interactive_plots/exceptions.py
my_interactive_plots/plots.py
my_interactive_plots/report_generator.py
my_interactive_plots/utils.py
my_interactive_plots/web_app.py
tests/__init__.py
tests/test_cli.py
tests/test_plots.py
my_interactive_plots-0.1.7.dist-info/LICENSE
my_interactive_plots-0.1.7.dist-info/METADATA
my_interactive_plots-0.1.7.dist-info/WHEEL
my_interactive_plots-0.1.7.dist-info/entry_points.txt
my_interactive_plots-0.1.7.dist-info/top_level.txt
my_interactive_plots-0.1.7.dist-info/RECORD
